yso/__init__.py
yso-0.0.1.dist-info/METADATA
yso-0.0.1.dist-info/WHEEL
yso-0.0.1.dist-info/top_level.txt
yso-0.0.1.dist-info/RECORD
